{"focal_juvenile_locations": [[264, 751], [910, 642], [1187, 762], [767, 805], [299, 826], [1253, 767]], "large_vs_female": "0", "number_small_male": 4, "large_vs_large": "0", "pairwise_distance_females": 527.93, "tank_id": "SS1", "small_courting": "0", "small_vs_female": "1", "pairwise_distance_large_males": "NA", "total_fish": 12, "comments": "Small blue male chases female out from behind plants at the beginin. She then hides from him while he chased away another small male.- Rachel Koeter", "large_courting": "0", "large_male_locations": [], "male_chased_juvenile": "0", "small_male_locations": [[713, 795], [865, 772], [205, 774], [943, 555]], "pairwise_distance_small_males": 442.5, "pairewise_distance_juvs": 531.22, "female_vs_male": "0", "date": "03-20-2016", "time_of_clip": "11min", "number_focal": 6, "intermediate_courting": "0", "int_vs_female": "0", "model_female_locations": [[798, 814], [1321, 742]], "int_vs_int": "0", "female_vs_female": "0", "large_vs_small": "0", "number_large_male": 0, "number_model_female": 2, "video_name": "/Volumes/THE MOLLUSK/common_garden_weekly_videos/short_videos/03_20_2016_SS1_11min.mp4"}