{"focal_juvenile_locations": [[1219, 288], [1357, 200], [985, 385], [301, 762], [315, 857], [338, 1002], [230, 970], [626, 981], [955, 1002], [757, 873], [1311, 961], [887, 977], [915, 1003]], "small_male_locations": [[1343, 740], [333, 939]], "observer": "Rachel Koeter", "male_chased_juvenile": "0", "pairwise_distance_small_males": 1029.42, "large_vs_female": "0", "number_small_male": 2, "large_vs_large": "0", "pairwise_distance_females": 218.09, "female_vs_male": "0", "date": "04-10-2016", "time_of_clip": "6min", "small_vs_small": "0", "tank_id": "SS1", "small_courting": "1", "small_vs_female": "0", "number_focal": 13, "pairewise_distance_juvs": 613.7, "pairwise_distance_large_males": "NA", "intermediate_courting": "0", "int_vs_female": "0", "model_female_locations": [[1398, 796], [1322, 899], [1507, 783], [1420, 552]], "comments": "Small male courted the female by mirroring her swimming", "int_vs_int": "0", "female_vs_female": "0", "large_vs_small": "0", "number_large_male": 0, "large_courting": "0", "large_male_locations": [], "number_model_female": 4, "total_fish": 19, "video_name": "/Volumes/THE MOLLUSK/common_garden_weekly_videos/short_videos/04_10_2016_SS1_6min.mp4"}